[
  {
    "WorkedBy": "Dawn Reynolds",
    "Client": "BPV106",
    "CategoryCriteria": "Group/Plan Mapping or Logic",
    "TotalHours": 33
  },
  {
    "WorkedBy": "Dawn Reynolds",
    "Client": "BPV106",
    "CategoryCriteria": "Plan Test Results Review",
    "TotalHours": 1
  },
  {
    "WorkedBy": "Dawn Reynolds",
    "Client": "BPV106",
    "CategoryCriteria": "Platform Global Mapping or Logic",
    "TotalHours": 18.5
  },
  {
    "WorkedBy": "Dawn Reynolds",
    "Client": "JMS000",
    "CategoryCriteria": "Other",
    "TotalHours": 5.5
  },
  {
    "WorkedBy": "Dawn Reynolds",
    "Client": "UAG137",
    "CategoryCriteria": "Corrective Action - Plan Build",
    "TotalHours": 7.5
  },
  {
    "WorkedBy": "Dawn Reynolds",
    "Client": "UAG137",
    "CategoryCriteria": "Plan Build - Standard",
    "TotalHours": 61.25
  },
  {
    "WorkedBy": "Dawn Reynolds",
    "Client": "UAG137",
    "CategoryCriteria": "Plan Test Results Review",
    "TotalHours": 3.25
  }
]